LICENSE
MANIFEST.in
README.md
README.rst
setup.cfg
setup.py
docs/README.md
wajig/__init__.py
wajig/commands.py
wajig/constants.py
wajig/debfile-deps.py
wajig/debfile.py
wajig/perform.py
wajig/shell.py
wajig/util.py
wajig.egg-info/PKG-INFO
wajig.egg-info/SOURCES.txt
wajig.egg-info/dependency_links.txt
wajig.egg-info/entry_points.txt
wajig.egg-info/requires.txt
wajig.egg-info/top_level.txt
wajig/bash_completion.d/wajig.bash