Metadata-Version: 2.1
Name: wajig
Version: 4.1.3
Summary: Debian/Ubuntu admin management tool
Home-page: https://wajig.togaware.com
Author: Graham Williams
Author-email: wajig@togaware.com
Keywords: debian ubuntu admin
Classifier: Development Status :: 5 - Production/Stable
Classifier: Environment :: Console
Classifier: Intended Audience :: End Users/Desktop
Classifier: License :: OSI Approved :: GNU General Public License v3 (GPLv3)
Classifier: Programming Language :: Python :: 3
License-File: LICENSE
Requires-Dist: distro
